npiv/__init__.py
npiv/dgp.py
npiv/estimators.py
npiv/nets.py
npiv/sieve.py
npiv-0.0.1.dist-info/METADATA
npiv-0.0.1.dist-info/WHEEL
npiv-0.0.1.dist-info/top_level.txt
npiv-0.0.1.dist-info/RECORD
