Metadata-Version: 2.1
Name: npiv
Version: 0.0.1
Summary: Nonparametric IV Toolbox for Python
Author-email: Luis Rafael Justin Hoderlein <first.last@yale.edu>
Project-URL: Homepage, https://github.com/khemritolya/npiv
Project-URL: Bug Tracker, https://github.com/khemritlya/npiv/issues
Classifier: Programming Language :: Python :: 3
Classifier: License :: OSI Approved :: MIT License
Classifier: Operating System :: OS Independent
Requires-Python: >=3.8
Requires-Dist: jax >=0.4.19
Requires-Dist: flax
Requires-Dist: optax
Requires-Dist: tqdm
